chaban/__init__.py
chaban/actions/__init__.py
chaban/actions/action.py
chaban/bots/__init__.py
chaban/bots/telegram_bot.py
chaban/bots/telegram_methods.py
chaban/config/__init__.py
chaban/config/global_settings.py
chaban/config/settings.py
chaban/core/__init__.py
chaban/core/exceptions.py
chaban/core/runner.py
chaban/handlers/__init__.py
chaban/handlers/base.py
chaban/handlers/exceptions.py
chaban/handlers/file_handlers.py
chaban/handlers/specials.py
chaban/handlers/text_handlers.py
chaban/utils/__init__.py
chaban/utils/singleton.py
chaban-0.1.1.dist-info/LICENSE
chaban-0.1.1.dist-info/METADATA
chaban-0.1.1.dist-info/WHEEL
chaban-0.1.1.dist-info/top_level.txt
chaban-0.1.1.dist-info/RECORD
