Metadata-Version: 2.1
Name: chaban
Version: 0.1.1
Summary: UNKNOWN
Home-page: https://github.com/ibrag8998/chaban/
Author: Ibrahim Gadzhimagomedov
Author-email: ibragdzh@gmail.com
License: UNKNOWN
Platform: UNKNOWN
Classifier: Programming Language :: Python :: 3
Classifier: License :: OSI Approved :: MIT License
Classifier: Operating System :: OS Independent
Requires-Python: >=3.8
Requires-Dist: httpx (==0.14.0)
